setup.py
ioStick/__init__.py
ioStick.egg-info/PKG-INFO
ioStick.egg-info/SOURCES.txt
ioStick.egg-info/dependency_links.txt
ioStick.egg-info/requires.txt
ioStick.egg-info/top_level.txt