Metadata-Version: 1.0
Name: ioStick
Version: 1.0
Summary: Python wrapper for webLinux IoStick
Home-page: http://wlinux.mobi/products/ioStick
Author: Tom Carter
Author-email: admin@wlinux.mobi
License: UNKNOWN
Platform: UNKNOWN
